genbit/__init__.py
genbit/genbit_metrics.py
genbit/gender_statistics.py
genbit/lemmatizer.py
genbit/metrics_calculation.py
genbit/overall_gender_statistics.py
genbit/tokenizer.py
genbit/version.py
genbit/word_based_gender_statistics.py
genbit/gendered-word-lists/de/female.txt
genbit/gendered-word-lists/de/male.txt
genbit/gendered-word-lists/en/female.txt
genbit/gendered-word-lists/en/male.txt
genbit/gendered-word-lists/en/non-binary.txt
genbit/gendered-word-lists/es/female.txt
genbit/gendered-word-lists/es/male.txt
genbit/gendered-word-lists/fr/female.txt
genbit/gendered-word-lists/fr/male.txt
genbit/gendered-word-lists/it/female.txt
genbit/gendered-word-lists/it/male.txt
genbit/gendered-word-lists/ru/female.txt
genbit/gendered-word-lists/ru/male.txt
genbit/tests/__init__.py
genbit/tests/test_language_support.py
genbit/tests/test_lemmatization.py
genbit/tests/test_metrics_calculation.py
genbit/tests/test_non_binary_gender.py
genbit/tests/test_tokenization.py
genbit/tests/test_trans_cis.py
genbit-2.2.0.0.dist-info/LICENSE
genbit-2.2.0.0.dist-info/METADATA
genbit-2.2.0.0.dist-info/WHEEL
genbit-2.2.0.0.dist-info/top_level.txt
genbit-2.2.0.0.dist-info/RECORD
