Metadata-Version: 2.1
Name: genbit
Version: 2.2.0.0
Home-page: https://github.com/microsoft/responsibleaitoolbox-genbit
Author: Microsoft
Author-email: raiwidgets-maintain@microsoft.com
License: MIT License
License-File: LICENSE
Requires-Dist: scipy (>=1.5.2)
Requires-Dist: numpy (>=1.21.5)
Requires-Dist: language-tags (==1.0.0)
Requires-Dist: stopwordsiso (==0.6.1)
Requires-Dist: parameterized (==0.7.4)
Requires-Dist: nltk (==3.6.6)
Requires-Dist: stanza (==1.2)
